tcloud-2.11.0.dist-info/licenses/LICENSE
tobikodata/__init__.py
tobikodata/tcloud/README.md
tobikodata/tcloud/__init__.py
tobikodata/tcloud/_version.py
tobikodata/tcloud/auth.py
tobikodata/tcloud/codespaces.py
tobikodata/tcloud/config.py
tobikodata/tcloud/constants.py
tobikodata/tcloud/installer.py
tobikodata/tcloud/jwt.py
tobikodata/tcloud/pip_helper.py
tobikodata/tcloud/py.typed
tobikodata/tcloud/utils.py
tobikodata/tcloud/cli/__init__.py
tobikodata/tcloud/cli/auth.py
tobikodata/tcloud/cli/main.py
tobikodata/tcloud/cli/project.py
tcloud-2.11.0.dist-info/METADATA
tcloud-2.11.0.dist-info/WHEEL
tcloud-2.11.0.dist-info/entry_points.txt
tcloud-2.11.0.dist-info/namespace_packages.txt
tcloud-2.11.0.dist-info/top_level.txt
tcloud-2.11.0.dist-info/RECORD
