Metadata-Version: 2.4
Name: tcloud
Version: 2.11.0
Author: TobikoData Inc.
Author-email: engineering@tobikodata.com
License: Apache License 2.0
Classifier: Intended Audience :: Developers
Classifier: Intended Audience :: Science/Research
Classifier: License :: OSI Approved :: Apache Software License
Classifier: Operating System :: OS Independent
Classifier: Programming Language :: SQL
Classifier: Programming Language :: Python :: 3 :: Only
Requires-Python: <3.13,>=3.9
License-File: LICENSE
Requires-Dist: authlib
Requires-Dist: click
Requires-Dist: cryptography<46.0.0
Requires-Dist: httpx
Requires-Dist: pyperclip
Requires-Dist: requests
Requires-Dist: rich[jupyter]
Requires-Dist: ruamel-yaml
Requires-Dist: tenacity
Dynamic: author
Dynamic: author-email
Dynamic: classifier
Dynamic: description
Dynamic: description-content-type
Dynamic: license
Dynamic: license-file
Dynamic: requires-dist
Dynamic: requires-python
